tasfiya/__init__.py
tasfiya/jsonxd.py
tasfiya/txt/fbav.txt
tasfiya/txt/fbav_old.txt
tasfiya/txt/fbcr.txt
tasfiya/txt/fbdm.txt
tasfiya-0.1.4.dist-info/METADATA
tasfiya-0.1.4.dist-info/WHEEL
tasfiya-0.1.4.dist-info/top_level.txt
tasfiya-0.1.4.dist-info/RECORD
